pyinels/__init__.py
pyinels/const.py
pyinels/exception.py
pyinels/pyTimer.py
pyinels/api/__init__.py
pyinels/api/resources.py
pyinels/device/__init__.py
pyinels/device/pyAiring.py
pyinels/device/pyBase.py
pyinels/device/pyDoor.py
pyinels/device/pyLight.py
pyinels/device/pyMeter.py
pyinels/device/pyShutter.py
pyinels/device/pySwitch.py
tests/__init__.py
tests/airing_test.py
tests/api_test.py
tests/const_test.py
tests/door_test.py
tests/examples.py
tests/light_test.py
tests/meter_test.py
tests/production_test.py
tests/real_worl_test.py
tests/resource_test.py
tests/shutter_test.py
tests/switch_test.py
tests/timer_test.py
pyinels_domenix_dev-0.2.5.dist-info/LICENSE
pyinels_domenix_dev-0.2.5.dist-info/METADATA
pyinels_domenix_dev-0.2.5.dist-info/WHEEL
pyinels_domenix_dev-0.2.5.dist-info/top_level.txt
pyinels_domenix_dev-0.2.5.dist-info/RECORD
